README.rst
setup.py
radiobabel/__init__.py
radiobabel/errors.py
radiobabel/test_utils.py
radiobabel.egg-info/PKG-INFO
radiobabel.egg-info/SOURCES.txt
radiobabel.egg-info/dependency_links.txt
radiobabel.egg-info/requires.txt
radiobabel.egg-info/top_level.txt
radiobabel/backends/__init__.py
radiobabel/backends/soundcloud.py
tests/test_soundcloud.py