Metadata-Version: 1.1
Name: radiobabel
Version: 0.1.0
Summary: Interact with a number of online music services using a single unified API.
Home-page: https://github.com/rehabradio/radiobabel
Author: Paddy Carey
Author-email: patrick@rehabstudio.com
License: UNKNOWN
Platform: UNKNOWN
Classifier: Development Status :: 2 - Pre-Alpha
Classifier: Programming Language :: Python
Classifier: Programming Language :: Python :: 2
Classifier: Programming Language :: Python :: 2.7
Classifier: Programming Language :: Python :: 3
Classifier: Programming Language :: Python :: 3.4
